[
  {
    "id": 1,
    "username": "值日生小陈",
    "avatar": "",
    "time": "2015-10-28 07:00",
    "content": "当值日生真的太烦了，每天要早到二十分钟扫地擦黑板，放学还要留下来倒垃圾拖地。关键是有些人吃完零食垃圾随手就扔地上，我刚扫完又脏了。能不能有点公德心？"
  },
  {
    "id": 2,
    "username": "同是值日生",
    "avatar": "",
    "time": "2015-10-28 07:20",
    "content": "深有同感。最烦的是擦黑板，粉笔灰飞得到处都是，擦完黑板自己变成白人了。而且有的老师写字特别用力，粉笔印怎么擦都擦不干净。"
  },
  {
    "id": 3,
    "username": "值日生小陈",
    "avatar": "",
    "time": "2015-10-28 12:30",
    "content": "对对对，还有倒垃圾也是个苦差事。垃圾桶超级重，要从四楼搬到一楼的垃圾站，楼梯又窄，每次都怕洒出来。上次垃圾袋破了，汤汤水水洒了一楼梯，我一个人擦了半小时。"
  },
  {
    "id": 4,
    "username": "逃值日专家",
    "avatar": "",
    "time": "2015-10-28 13:00",
    "content": "所以我每次轮到值日都找人换，请人喝瓶水就行了。实在换不了就随便扫两下应付一下，反正也没人检查得那么仔细。"
  },
  {
    "id": 5,
    "username": "值日生小陈",
    "avatar": "",
    "time": "2015-10-28 17:45",
    "content": "就是因为有你这种人，值日才这么累。你随便扫两下，检查的时候扣分了，第二天值日的人就要加倍打扫。"
  },
  {
    "id": 6,
    "username": "班长来了",
    "avatar": "",
    "time": "2015-10-28 18:30",
    "content": "以后值日不认真的我记名字，累计三次找班主任谈话。大家都是一个班的，值日是大家的事，不要总想着偷懒。"
  }
]
